{
  "source": "traffic_forecast_model",
  "generated_at": "2026-05-18T03:33:13+09:00",
  "feature_datetime": "2026-05-18T03:00:00+09:00",
  "target_datetime": "2026-05-18T04:00:00+09:00",
  "horizon_hours": 1,
  "model_target": "target_traffic_volume_proxy_t_plus_1h",
  "forecast_fields": [
    "predicted_traffic_volume_proxy",
    "predicted_traffic_volume_score",
    "predicted_congestion_score",
    "predicted_avg_speed_kmh"
  ],
  "current_traffic_meta": {
    "source": "citydata_road_traffic_dong_filtered",
    "collected_at": "2026-05-17T18:33:02.070Z",
    "extracted_at": "2026-05-17T18:33:09.742Z",
    "citydata_path": "data/raw/citydata/2026-05-18/0333.json",
    "total_links_scanned": 293,
    "dong_filtered_count": 264,
    "dong_summary_count": 9,
    "target_dongs": [
      "역삼1동",
      "역삼2동",
      "논현1동",
      "논현2동",
      "삼성1동",
      "삼성2동",
      "신사동",
      "청담동",
      "대치4동"
    ]
  },
  "note": "Traffic volume is predicted by a TOPIS-trained ML model. Congestion and speed are live-calibrated estimates using current Seoul citydata road observations.",
  "regions": [
    {
      "dong_name": "논현1동",
      "predicted_traffic_volume_proxy": 4750.989,
      "predicted_traffic_volume_score": 1.0,
      "predicted_congestion_score": 0.7842,
      "predicted_avg_speed_kmh": 22.2,
      "current_congestion_score": 0.432,
      "current_avg_speed_kmh": 25.6,
      "current_link_count": 19,
      "live_calibration_multiplier": 0.946
    },
    {
      "dong_name": "청담동",
      "predicted_traffic_volume_proxy": 3066.318,
      "predicted_traffic_volume_score": 0.6201,
      "predicted_congestion_score": 0.5741,
      "predicted_avg_speed_kmh": 25.0,
      "current_congestion_score": 0.499,
      "current_avg_speed_kmh": 25.7,
      "current_link_count": 33,
      "live_calibration_multiplier": 0.9783
    },
    {
      "dong_name": "신사동",
      "predicted_traffic_volume_proxy": 2237.978,
      "predicted_traffic_volume_score": 0.4333,
      "predicted_congestion_score": 0.4104,
      "predicted_avg_speed_kmh": 41.4,
      "current_congestion_score": 0.373,
      "current_avg_speed_kmh": 42.0,
      "current_link_count": 47,
      "live_calibration_multiplier": 0.8165
    },
    {
      "dong_name": "삼성1동",
      "predicted_traffic_volume_proxy": 1611.212,
      "predicted_traffic_volume_score": 0.292,
      "predicted_congestion_score": 0.3505,
      "predicted_avg_speed_kmh": 26.6,
      "current_congestion_score": 0.446,
      "current_avg_speed_kmh": 25.7,
      "current_link_count": 12,
      "live_calibration_multiplier": 0.9517
    },
    {
      "dong_name": "대치4동",
      "predicted_traffic_volume_proxy": 588.099,
      "predicted_traffic_volume_score": 0.0613,
      "predicted_congestion_score": 0.2877,
      "predicted_avg_speed_kmh": 19.5,
      "current_congestion_score": 0.657,
      "current_avg_speed_kmh": 17.1,
      "current_link_count": 18,
      "live_calibration_multiplier": 1.1647
    },
    {
      "dong_name": "삼성2동",
      "predicted_traffic_volume_proxy": 508.662,
      "predicted_traffic_volume_score": 0.0434,
      "predicted_congestion_score": 0.2294,
      "predicted_avg_speed_kmh": 27.3,
      "current_congestion_score": 0.533,
      "current_avg_speed_kmh": 24.5,
      "current_link_count": 23,
      "live_calibration_multiplier": 1.0102
    },
    {
      "dong_name": "역삼1동",
      "predicted_traffic_volume_proxy": 501.024,
      "predicted_traffic_volume_score": 0.0417,
      "predicted_congestion_score": 0.2219,
      "predicted_avg_speed_kmh": 27.0,
      "current_congestion_score": 0.516,
      "current_avg_speed_kmh": 24.3,
      "current_link_count": 91,
      "live_calibration_multiplier": 1.0043
    },
    {
      "dong_name": "역삼2동",
      "predicted_traffic_volume_proxy": 316.243,
      "predicted_traffic_volume_score": 0.0,
      "predicted_congestion_score": 0.1771,
      "predicted_avg_speed_kmh": 30.6,
      "current_congestion_score": 0.466,
      "current_avg_speed_kmh": 27.6,
      "current_link_count": 19,
      "live_calibration_multiplier": 0.938
    },
    {
      "dong_name": "논현2동",
      "predicted_traffic_volume_proxy": 928.14,
      "predicted_traffic_volume_score": 0.138,
      "predicted_congestion_score": 0.1615,
      "predicted_avg_speed_kmh": 44.3,
      "current_congestion_score": 0.2,
      "current_avg_speed_kmh": 43.7,
      "current_link_count": 2,
      "live_calibration_multiplier": 0.75
    }
  ]
}
