{
  "source": "traffic_forecast_model",
  "generated_at": "2026-05-15T01:51:57+09:00",
  "feature_datetime": "2026-05-15T01:00:00+09:00",
  "target_datetime": "2026-05-15T02:00:00+09:00",
  "horizon_hours": 1,
  "model_target": "target_traffic_volume_proxy_t_plus_1h",
  "forecast_fields": [
    "predicted_traffic_volume_proxy",
    "predicted_traffic_volume_score",
    "predicted_congestion_score",
    "predicted_avg_speed_kmh"
  ],
  "current_traffic_meta": {
    "source": "citydata_road_traffic_dong_filtered",
    "collected_at": "2026-05-14T16:51:47.258Z",
    "extracted_at": "2026-05-14T16:51:54.612Z",
    "citydata_path": "data/raw/citydata/2026-05-15/0151.json",
    "total_links_scanned": 293,
    "dong_filtered_count": 264,
    "dong_summary_count": 9,
    "target_dongs": [
      "역삼1동",
      "역삼2동",
      "논현1동",
      "논현2동",
      "삼성1동",
      "삼성2동",
      "신사동",
      "청담동",
      "대치4동"
    ]
  },
  "note": "Traffic volume is predicted by a TOPIS-trained ML model. Congestion and speed are live-calibrated estimates using current Seoul citydata road observations.",
  "regions": [
    {
      "dong_name": "논현1동",
      "predicted_traffic_volume_proxy": 4926.141,
      "predicted_traffic_volume_score": 1.0,
      "predicted_congestion_score": 0.8377,
      "predicted_avg_speed_kmh": 18.2,
      "current_congestion_score": 0.573,
      "current_avg_speed_kmh": 20.2,
      "current_link_count": 19,
      "live_calibration_multiplier": 1.084
    },
    {
      "dong_name": "청담동",
      "predicted_traffic_volume_proxy": 2396.957,
      "predicted_traffic_volume_score": 0.4361,
      "predicted_congestion_score": 0.4376,
      "predicted_avg_speed_kmh": 26.2,
      "current_congestion_score": 0.44,
      "current_avg_speed_kmh": 26.2,
      "current_link_count": 33,
      "live_calibration_multiplier": 0.9425
    },
    {
      "dong_name": "신사동",
      "predicted_traffic_volume_proxy": 1930.251,
      "predicted_traffic_volume_score": 0.3321,
      "predicted_congestion_score": 0.3518,
      "predicted_avg_speed_kmh": 39.4,
      "current_congestion_score": 0.384,
      "current_avg_speed_kmh": 38.9,
      "current_link_count": 47,
      "live_calibration_multiplier": 0.822
    },
    {
      "dong_name": "삼성1동",
      "predicted_traffic_volume_proxy": 1133.412,
      "predicted_traffic_volume_score": 0.1544,
      "predicted_congestion_score": 0.3017,
      "predicted_avg_speed_kmh": 25.6,
      "current_congestion_score": 0.542,
      "current_avg_speed_kmh": 23.5,
      "current_link_count": 12,
      "live_calibration_multiplier": 1.0272
    },
    {
      "dong_name": "대치4동",
      "predicted_traffic_volume_proxy": 807.74,
      "predicted_traffic_volume_score": 0.0818,
      "predicted_congestion_score": 0.297,
      "predicted_avg_speed_kmh": 22.8,
      "current_congestion_score": 0.648,
      "current_avg_speed_kmh": 20.1,
      "current_link_count": 18,
      "live_calibration_multiplier": 1.1228
    },
    {
      "dong_name": "역삼1동",
      "predicted_traffic_volume_proxy": 723.695,
      "predicted_traffic_volume_score": 0.0631,
      "predicted_congestion_score": 0.2413,
      "predicted_avg_speed_kmh": 24.5,
      "current_congestion_score": 0.532,
      "current_avg_speed_kmh": 22.1,
      "current_link_count": 91,
      "live_calibration_multiplier": 1.0397
    },
    {
      "dong_name": "논현2동",
      "predicted_traffic_volume_proxy": 1183.754,
      "predicted_traffic_volume_score": 0.1656,
      "predicted_congestion_score": 0.2296,
      "predicted_avg_speed_kmh": 30.5,
      "current_congestion_score": 0.334,
      "current_avg_speed_kmh": 29.3,
      "current_link_count": 2,
      "live_calibration_multiplier": 0.8508
    },
    {
      "dong_name": "역삼2동",
      "predicted_traffic_volume_proxy": 440.81,
      "predicted_traffic_volume_score": 0.0,
      "predicted_congestion_score": 0.2113,
      "predicted_avg_speed_kmh": 28.3,
      "current_congestion_score": 0.556,
      "current_avg_speed_kmh": 25.0,
      "current_link_count": 19,
      "live_calibration_multiplier": 1.0155
    },
    {
      "dong_name": "삼성2동",
      "predicted_traffic_volume_proxy": 654.377,
      "predicted_traffic_volume_score": 0.0476,
      "predicted_congestion_score": 0.1956,
      "predicted_avg_speed_kmh": 27.8,
      "current_congestion_score": 0.437,
      "current_avg_speed_kmh": 25.5,
      "current_link_count": 23,
      "live_calibration_multiplier": 0.9497
    }
  ]
}
